aiomangadex/__init__.py
aiomangadex/chapter.py
aiomangadex/language.py
aiomangadex/manga.py
aiomangadex-1.0.0.dist-info/LICENSE.txt
aiomangadex-1.0.0.dist-info/METADATA
aiomangadex-1.0.0.dist-info/WHEEL
aiomangadex-1.0.0.dist-info/top_level.txt
aiomangadex-1.0.0.dist-info/RECORD
