Metadata-Version: 2.1
Name: aiomangadex
Version: 1.0.0
Summary: A simple asynchronous API wrapper for mangadex.org.
Home-page: https://github.com/lukesaltweather/aiomangadex
Author: lukesaltweather
Author-email: lukesaltweather@gmail.com
License: Apache License 2.0
Platform: UNKNOWN
Classifier: Programming Language :: Python :: 3.7
Classifier: Programming Language :: Python :: 3.8
Classifier: License :: OSI Approved :: Apache Software License
Classifier: Development Status :: 4 - Beta
Requires-Dist: aiohttp
